RequestsExtension/ApiLibKeywords.py
RequestsExtension/__init__.py
RequestsExtension/version.py
robotframework_requests_extension-0.0.1.dist-info/LICENSE.md
robotframework_requests_extension-0.0.1.dist-info/METADATA
robotframework_requests_extension-0.0.1.dist-info/WHEEL
robotframework_requests_extension-0.0.1.dist-info/top_level.txt
robotframework_requests_extension-0.0.1.dist-info/RECORD
