Metadata-Version: 2.1
Name: robotframework-requests-extension
Version: 0.0.1
Summary: RequestsLibrary Extension
Home-page: UNKNOWN
Author: Vincenzo Gasparo
Author-email: vincenzo.gasparo@gmail.it
Maintainer: Vincenzo Gasparo
Maintainer-email: vincenzo.gasparo@gmail.it
License: MIT
Keywords: robotframework testing test automation http client requests
Platform: any
Classifier: Development Status :: 2 - Pre-Alpha
Classifier: License :: OSI Approved :: MIT License
Classifier: Operating System :: OS Independent
Classifier: Programming Language :: Python
Classifier: Topic :: Software Development :: Testing
Requires-Dist: robotframework
Requires-Dist: robotframework-requests
Requires-Dist: requests
Requires-Dist: jsonschema
